README.md
setup.py
bin/enigma-features
bin/eprover
bin/predict
bin/train
enigmatic/__init__.py
enigmatic/enigmap.py
enigmatic/liblinear.py
enigmatic/models.py
enigmatic/pretrains.py
enigmatic/protos.py
enigmatic/trains.py
enigmatic/xgbooster.py
enigmatic.egg-info/PKG-INFO
enigmatic.egg-info/SOURCES.txt
enigmatic.egg-info/dependency_links.txt
enigmatic.egg-info/not-zip-safe
enigmatic.egg-info/requires.txt
enigmatic.egg-info/top_level.txt
enigmatic/learn/__init__.py
enigmatic/learn/learner.py
enigmatic/learn/lgbooster.py
enigmatic/learn/liblinear.py
enigmatic/learn/xgbooster.py