Metadata-Version: 1.0
Name: enigmatic
Version: 0.1.1
Summary: Enigma: Automatic Inference Guiding Machine
Home-page: http://github.com/ai4reason/enigmatic
Author: ai4reason
Author-email: UNKNOWN
License: GPL3
Platform: UNKNOWN
